ingen/__init__.py
ingen/core.py
ingen/metrics.py
ingen/visualizer.py
intergen/__init__.py
intergen/core.py
intergen/metrics.py
intergen/visualizer.py
intergen-0.1.0.dist-info/METADATA
intergen-0.1.0.dist-info/WHEEL
intergen-0.1.0.dist-info/top_level.txt
intergen-0.1.0.dist-info/RECORD
