Metadata-Version: 2.1
Name: intergen
Version: 0.1.0
Summary: INTERGEN: Interactive Neural Generalization Framework
Home-page: https://github.com/yourusername/intergen
Author: Mustafa Ekmekci
Classifier: Programming Language :: Python :: 3
Classifier: License :: OSI Approved :: MIT License
Requires-Dist: numpy
Requires-Dist: pandas
Requires-Dist: matplotlib
Requires-Dist: seaborn
Requires-Dist: tensorflow
Requires-Dist: scikit-learn
